{
  "$schema": "https://json.schemastore.org/tsconfig",
  "compilerOptions": {
    "jsx": "react-native",
    "types": ["react-native"],
    "lib": ["ESNext", "DOM"],
    "target": "ESNext",
    "module": "ESNext",
    "moduleResolution": "Bundler",
    "esModuleInterop": true,
    "isolatedModules": true,
    "resolveJsonModule": true,
    "allowImportingTsExtensions": true,
    "allowSyntheticDefaultImports": true,
    "forceConsistentCasingInFileNames": true,
    "useDefineForClassFields": true,
    "noUnusedParameters": true,
    "noUnusedLocals": true,
    "noEmit": true,
    "strict": true,
    "allowJs": true,
    "skipLibCheck": true
  },
  "exclude": [
    "node_modules"
  ]
}